{"stat.walkOneCm":97218,"stat.leaveGame":9,"stat.useItem.minecraft.gold_ore":17,"stat.drop.minecraft.redstone":6,"stat.pickup.botania.manaresource":1,"stat.pickup.contenttweaker.mana_powder":4,"stat.pickup.everlastingabilities.ability_bottle":1,"stat.jump":163,"stat.fallOneCm":1236,"stat.pickup.thaumcraft.stone_arcane":4,"stat.crouchOneCm":525,"stat.useItem.astralsorcery.itemusabledust":4,"stat.pickup.minecraft.sapling":24,"stat.sprintOneCm":15767,"stat.useItem.minecraft.stone_slab2":889,"stat.pickup.minecraft.apple":2,"stat.pickup.wizardry.wisdom_wood_log":1,"stat.useItem.minecraft.sapling":3,"stat.pickup.thaumcraft.crystal_essence":68,"stat.pickup.minecraft.grass":1,"stat.damageTaken":100,"stat.useItem.astralsorcery.blockcustomore":1,"stat.pickup.astralsorcery.blockcustomore":1,"stat.flyOneCm":113187,"stat.drop":9,"stat.playOneMinute":108087,"stat.sneakTime":408,"stat.damageDealt":30,"stat.pickup.minecraft.redstone":3,"stat.timeSinceDeath":108087,"stat.drop.minecraft.log":1,"stat.drop.minecraft.diamond":1,"stat.drop.minecraft.grass":1}